uuid6/__init__.py
uuid6/py.typed
uuid6-2023.4.25.dist-info/LICENSE
uuid6-2023.4.25.dist-info/METADATA
uuid6-2023.4.25.dist-info/WHEEL
uuid6-2023.4.25.dist-info/top_level.txt
uuid6-2023.4.25.dist-info/RECORD
