Metadata-Version: 2.1
Name: uuid6
Version: 2023.4.25
Summary: New time-based UUID formats which are suited for use as a database key
Home-page: https://github.com/oittaa/uuid6-python
Author: Oittaa
Author-email: 
Keywords: uuid,uuid6,uuid7,uuid8,uuidv6,uuidv7,uuidv8
Classifier: Development Status :: 3 - Alpha
Classifier: Intended Audience :: Developers
Classifier: License :: OSI Approved :: MIT License
Classifier: Operating System :: OS Independent
Classifier: Programming Language :: Python
Classifier: Programming Language :: Python :: 3
Classifier: Programming Language :: Python :: 3.8
Classifier: Programming Language :: Python :: 3.9
Classifier: Programming Language :: Python :: 3.10
Classifier: Programming Language :: Python :: 3.11
Requires-Python: >=3.8
License-File: LICENSE
